cdipy/__init__.py
cdipy/cdipy.py
cdipy/chrome.py
cdipy/exceptions.py
cdipy/protocol.py
cdipy/utils.py
cdipy-0.4.4.dist-info/licenses/LICENSE.md
cdipy-0.4.4.dist-info/METADATA
cdipy-0.4.4.dist-info/WHEEL
cdipy-0.4.4.dist-info/top_level.txt
cdipy-0.4.4.dist-info/RECORD
