Metadata-Version: 2.4
Name: cdipy
Version: 0.4.4
Summary: An async Python interface for Chrome Devtools
Home-page: https://github.com/pilate/cdipy
Author: Pilate
Author-email: pilate@pilate.es
License: MIT License
Requires-Python: >=3.8
License-File: LICENSE.md
Requires-Dist: aiohttp<3.14.0
Requires-Dist: msgspec<0.21.0
Requires-Dist: pyee<13.0.0
Requires-Dist: websockets<=15
Dynamic: license-file
